platypus_python/__init__.py
platypus_python-1.0.3.dist-info/METADATA
platypus_python-1.0.3.dist-info/WHEEL
platypus_python-1.0.3.dist-info/top_level.txt
platypus_python-1.0.3.dist-info/RECORD
